myselfutilsyjl/__init__.py
myselfutilsyjl/mu.py
myselfutilsyjl/plot_draw_metric.py
myselfutilsyjl-1.0.8.dist-info/METADATA
myselfutilsyjl-1.0.8.dist-info/WHEEL
myselfutilsyjl-1.0.8.dist-info/top_level.txt
myselfutilsyjl-1.0.8.dist-info/RECORD
