Metadata-Version: 2.1
Name: myselfutilsyjl
Version: 1.0.8
Summary: 自己常用的工具包，注释稀少，仅供自己使用  --姚金良
Home-page: https://github.com/yaojinliang/myselfutilsyjl/tree/main/dist
Author: yjl
Author-email: 1904782387@qq.com
License: 不知道是啥
Platform: UNKNOWN
Classifier: Programming Language :: Python
Classifier: Operating System :: Microsoft :: Windows
Classifier: Operating System :: Unix
Classifier: Programming Language :: Python :: 2.7
Classifier: Programming Language :: Python :: 3.7
Requires-Dist: numpy
Requires-Dist: matplotlib
Requires-Dist: scikit-learn
